stepspy/__init__.py
stepspy/pouch.py
stepspy/stepspy.py
stepspy/libsteps/__init__.py
stepspy/libsteps/pylibsteps.py
stepspy-dev/__init__.py
stepspy-dev/pouch.py
stepspy-dev/stepspy.py
stepspy-dev/libsteps/__init__.py
stepspy-dev/libsteps/pylibsteps.py
stepspy-2.2.1.dist-info/LICENSE
stepspy-2.2.1.dist-info/METADATA
stepspy-2.2.1.dist-info/WHEEL
stepspy-2.2.1.dist-info/top_level.txt
stepspy-2.2.1.dist-info/RECORD
