Metadata-Version: 2.1
Name: stepspy
Version: 2.2.1
Summary: Python module of Simulation Toolkit for Electrical Power Systems
Home-page: https://github.com/changgang/steps
Author: Changgang Li
Author-email: lichgang@sdu.edu.cn
License: UNKNOWN
Platform: UNKNOWN
Classifier: Programming Language :: Python :: 3
Classifier: License :: OSI Approved :: MIT License
Classifier: Operating System :: OS Independent
